Itachi-0.0.1rc1.dist-info/METADATA
Itachi-0.0.1rc1.dist-info/RECORD
Itachi-0.0.1rc1.dist-info/WHEEL
Itachi-0.0.1rc1.dist-info/entry_points.txt
Itachi-0.0.1rc1.dist-info/top_level.txt
bakend/__init__.py
bakend/bert/__init__.py
bakend/bert/create_pretraining_data.py
bakend/bert/extract_features.py
bakend/bert/modeling.py
bakend/bert/modeling_test.py
bakend/bert/optimization.py
bakend/bert/optimization_test.py
bakend/bert/run_classifier.py
bakend/bert/run_classifier_with_tfhub.py
bakend/bert/run_pretraining.py
bakend/bert/run_squad.py
bakend/bert/tokenization.py
bakend/bert/tokenization_test.py
bakend/char2vec/__init__.py
bakend/char2vec/get_embeddings_matrix.py
dataset/__init__.py
itachi/__init__.py
itachi/__main__.py
itachi/version.py
itachi/commands/__init__.py
itachi/commands/predict.py
itachi/commands/subcommand.py
itachi/commands/test.py
itachi/commands/train.py
itachi/common/__init__.py
itachi/common/checks.py
itachi/common/file_utils.py
itachi/common/from_params.py
itachi/common/lazy.py
itachi/common/logging.py
itachi/common/params.py
itachi/common/registrable.py
itachi/common/tee.py
itachi/common/tqdm.py
itachi/common/util.py
itachi/data/__init__.py
itachi/data/batch.py
itachi/data/instance.py
itachi/data/vocabulary.py
itachi/data/dataset_readers/__init__.py
itachi/data/dataset_readers/dataset_reader.py
itachi/data/dataset_readers/text_classifier_dataset_reader.py
itachi/layers/__init__.py
itachi/models/__init__.py
itachi/models/archival.py
itachi/models/model.py
itachi/models/intent_slot/__init__.py
itachi/models/intent_slot/intent_slot_model.py
itachi/models/intent_slot/sf_id_intent_slot_model.py
itachi/models/text_classifier/__init__.py
itachi/models/text_classifier/aver_pooling_text_classifier_model.py
itachi/models/text_classifier/bert_text_classifier_model.py
itachi/models/text_classifier/cnn_test_classifier.py
itachi/models/text_classifier/text_classifier_model.py
itachi/modules/__init__.py
itachi/predictors/__init__.py
itachi/predictors/predictor.py
itachi/predictors/text_classifier_predictor.py
